jllib/__init__.py
jllib/deeplearning.py
jllib/plotting.py
jllib/models/__init__.py
jllib/models/cnn.py
jllib/models/encoder.py
jllib/models/fcn.py
jllib/models/inception.py
jllib/models/mcdcnn.py
jllib/models/mcnn.py
jllib/models/mlp.py
jllib/models/resnet.py
jllib/models/tlenet.py
jllib/models/twiesn.py
jllib/utils/__init__.py
jllib/utils/constants.py
jllib/utils/utils.py
jllib-0.0.70.dist-info/LICENSE
jllib-0.0.70.dist-info/METADATA
jllib-0.0.70.dist-info/WHEEL
jllib-0.0.70.dist-info/top_level.txt
jllib-0.0.70.dist-info/RECORD
