Metadata-Version: 2.1
Name: jllib
Version: 0.0.70
Summary: UNKNOWN
Home-page: https://example.org
Author: Jonathan Liebers
Author-email: git@jo2k.de
License: UNKNOWN
Platform: UNKNOWN
Classifier: Programming Language :: Python :: 3
Classifier: License :: OSI Approved :: GNU General Public License v3 (GPLv3)
Classifier: Operating System :: OS Independent
Requires-Python: >=3.7
Requires-Dist: pandas (>=1.2.0)
Requires-Dist: tensorflow (>=2.5.0)
Requires-Dist: tensorflow-addons (>=0.12.1)
Requires-Dist: matplotlib (>=3.3.0)
Requires-Dist: tqdm (>=4.56.0)
Requires-Dist: scikit-learn (>=0.24.0)
Requires-Dist: wheel
Requires-Dist: twine
